logistic_dml/__init__.py
logistic_dml/logistic_dml.py
logistic_dml/pdev.py
logistic_dml/pdev_lr.py
logistic_dml/pdev_rf.py
logistic_dml/test_logistic_dml.py
logistic_dml/test_network_kernel.py
logistic_dml-1.1.0.dist-info/METADATA
logistic_dml-1.1.0.dist-info/WHEEL
logistic_dml-1.1.0.dist-info/top_level.txt
logistic_dml-1.1.0.dist-info/RECORD
