Metadata-Version: 2.1
Name: logistic-dml
Version: 1.1.0
Summary: Python implementation of Logistic Double ML
Home-page: https://github.com/sdamerdji/logistic_dml
Author: damerdji
Author-email: salim.damerdji@stats.ox.ac.uk
License: UNKNOWN
Platform: UNKNOWN
Requires-Dist: pandas (>=1.5.2)
Requires-Dist: scipy (>=1.9.3)
Requires-Dist: numpy (>=1.23.5)
Requires-Dist: scikit-learn (>=1.3.0)
